mailslurp_client/__init__.py
mailslurp_client/api_client.py
mailslurp_client/configuration.py
mailslurp_client/exceptions.py
mailslurp_client/rest.py
mailslurp_client/api/__init__.py
mailslurp_client/api/ai_controller_api.py
mailslurp_client/api/alias_controller_api.py
mailslurp_client/api/attachment_controller_api.py
mailslurp_client/api/bounce_controller_api.py
mailslurp_client/api/bulk_actions_controller_api.py
mailslurp_client/api/common_actions_controller_api.py
mailslurp_client/api/connector_controller_api.py
mailslurp_client/api/consent_controller_api.py
mailslurp_client/api/contact_controller_api.py
mailslurp_client/api/domain_controller_api.py
mailslurp_client/api/email_controller_api.py
mailslurp_client/api/email_verification_controller_api.py
mailslurp_client/api/expired_controller_api.py
mailslurp_client/api/export_controller_api.py
mailslurp_client/api/form_controller_api.py
mailslurp_client/api/group_controller_api.py
mailslurp_client/api/guest_portal_controller_api.py
mailslurp_client/api/imap_controller_api.py
mailslurp_client/api/inbox_controller_api.py
mailslurp_client/api/inbox_forwarder_controller_api.py
mailslurp_client/api/inbox_replier_controller_api.py
mailslurp_client/api/mail_server_controller_api.py
mailslurp_client/api/mfa_controller_api.py
mailslurp_client/api/missed_email_controller_api.py
mailslurp_client/api/o_auth_connection_api.py
mailslurp_client/api/phone_controller_api.py
mailslurp_client/api/ruleset_controller_api.py
mailslurp_client/api/sent_emails_controller_api.py
mailslurp_client/api/sms_controller_api.py
mailslurp_client/api/template_controller_api.py
mailslurp_client/api/tools_controller_api.py
mailslurp_client/api/tracking_controller_api.py
mailslurp_client/api/user_controller_api.py
mailslurp_client/api/wait_for_controller_api.py
mailslurp_client/api/webhook_controller_api.py
mailslurp_client/models/__init__.py
mailslurp_client/models/abstract_webhook_payload.py
mailslurp_client/models/account_bounce_block_dto.py
mailslurp_client-17.0.0.dist-info/LICENSE
mailslurp_client-17.0.0.dist-info/METADATA
mailslurp_client-17.0.0.dist-info/WHEEL
mailslurp_client-17.0.0.dist-info/top_level.txt
mailslurp_client-17.0.0.dist-info/RECORD
