Metadata-Version: 2.1
Name: mailslurp-client
Version: 17.0.0
Summary: Official MailSlurp Python SDK Email API
Home-page: https://www.mailslurp.com/python
Author: MailSlurp
Author-email: contact@mailslurp.dev
License: UNKNOWN
Keywords: MailSlurp,Email,SMTP,Mailer,MailSlurp API,Test
Platform: UNKNOWN
Requires-Dist: urllib3 (>=1.15)
Requires-Dist: six (>=1.10)
Requires-Dist: certifi
Requires-Dist: python-dateutil
